{"uboDetails": [{"ownedStake": 0.033335, "Name": "Ejner S\u00f8rensen", "minOwnedStake": 1.0, "Valu8Id": 201779305, "maxOwnedStake": 1.0}, {"ownedStake": 0.041256229374999995, "Name": "Janne Beyer Trudslev", "minOwnedStake": 1.0, "Valu8Id": 201880022, "maxOwnedStake": 1.0}, {"ownedStake": 0.000412520625, "Name": "Ejner S\u00f8rensen", "minOwnedStake": 1.0, "Valu8Id": 201779305, "maxOwnedStake": 1.0}, {"ownedStake": 0.041256229374999995, "Name": "Camilla Beyer S\u00f8rensen", "minOwnedStake": 1.0, "Valu8Id": 202010624, "maxOwnedStake": 1.0}, {"ownedStake": 4.166875e-06, "Name": "Ejner S\u00f8rensen", "minOwnedStake": 1.0, "Valu8Id": 201779305, "maxOwnedStake": 1.0}, {"ownedStake": 0.041256229374999995, "Name": "Rikke Klitg\u00e5rd Beyer S\u00f8rensen", "minOwnedStake": 1.0, "Valu8Id": 201779308, "maxOwnedStake": 1.0}, {"ownedStake": 0.05, "Name": "Morten M\u00f8ller Vangsted", "minOwnedStake": 1.0, "Valu8Id": 201744157, "maxOwnedStake": 1.0}], "relationshipDetails": [{"OwnedStake": "1", "MaxOwnedVotes": "1", "endNodeID": 7675270, "PenneoRoleCode": "OW", "InDate": "2005-09-21", "startNodeID": 7993267}, {"OwnedStake": "1", "MaxOwnedVotes": "1", "endNodeID": 7993267, "PenneoRoleCode": "OW", "InDate": "2023-05-17", "startNodeID": 250744692}, {"OwnedStake": "0.25", "MaxOwnedVotes": "0.25", "endNodeID": 250744692, "PenneoRoleCode": "OW", "InDate": "2023-05-17", "startNodeID": 16129576}, {"OwnedStake": "0.6667", "MaxOwnedVotes": "0.6667", "endNodeID": 16129576, "PenneoRoleCode": "OW", "InDate": "2020-01-31", "startNodeID": 7824427}, {"OwnedStake": "0.2", "MaxOwnedVotes": "1", "endNodeID": 7824427, "PenneoRoleCode": "OW", "InDate": "2019-12-20", "startNodeID": 124617525}, {"OwnedStake": "1", "MaxOwnedVotes": "1", "endNodeID": 124617525, "PenneoRoleCode": "OW", "InDate": "2019-12-20", "startNodeID": 201779305}, {"OwnedStake": "0.25", "endNodeID": 7824427, "PenneoRoleCode": "OW", "InDate": "2019-12-20", "startNodeID": 124617513}, {"OwnedStake": "0.9901", "endNodeID": 124617513, "PenneoRoleCode": "OW", "InDate": "2019-12-20", "startNodeID": 201880022}, {"OwnedStake": "0.0099", "MaxOwnedVotes": "1", "endNodeID": 124617513, "PenneoRoleCode": "OW", "InDate": "2019-12-20", "startNodeID": 201779305}, {"OwnedStake": "0.25", "endNodeID": 7824427, "PenneoRoleCode": "OW", "InDate": "2019-12-20", "startNodeID": 124617497}, {"OwnedStake": "0.9901", "endNodeID": 124617497, "PenneoRoleCode": "OW", "InDate": "2019-12-20", "startNodeID": 202010624}, {"OwnedStake": "0.0001", "endNodeID": 124617497, "PenneoRoleCode": "OW", "InDate": "2019-12-20", "startNodeID": 201779305}, {"OwnedStake": "0.25", "endNodeID": 7824427, "PenneoRoleCode": "OW", "InDate": "2019-12-20", "startNodeID": 124617692}, {"OwnedStake": "0.9901", "endNodeID": 124617692, "PenneoRoleCode": "OW", "InDate": "2019-12-20", "startNodeID": 201779308}, {"OwnedStake": "0.0099", "MaxOwnedVotes": "1", "endNodeID": 124617692, "PenneoRoleCode": "OW", "InDate": "2019-12-20", "startNodeID": 201779305}, {"OwnedStake": "0.2", "MaxOwnedVotes": "0.2", "endNodeID": 16129576, "PenneoRoleCode": "OW", "InDate": "2023-06-15", "startNodeID": 252497135}, {"OwnedStake": "1", "MaxOwnedVotes": "1", "endNodeID": 252497135, "PenneoRoleCode": "OW", "InDate": "2023-06-15", "startNodeID": 201744157}], "nodes": [{"OperationalStatus": "Active", "LFY": "2022-12-31", "Phone": "96312500", "LegalForm": "Limited_company", "Website": "www.euro-poultry.com/", "label": "Company", "CompanyInfoUpdatedDate": "2023-10-02", "DescriptionEN": "The objects of the company are trade, crafts, industry and finance", "Signatory": "Selskabet tegnes af\u00a0direkt\u00f8ren.", "ParentCompanyName": "EURO POULTRY HOLDING ApS", "Name": "House of Foods A/S", "KeyPersonsUpdatedDate": "2023-10-14", "FiscalYearLength": 12.0, "RegistrationDate": "1999-11-26", "DataUpdatedDate": "2023-11-02", "OwnersUpdatedDate": "2022-09-11", "ListingType": "Unlisted", "OrgNo": "25054741", "FinancialDataCurrencyCode": "USD", "HasForeignUltimateParent": false, "Valu8Id": 7675270, "PreviousNames": "EURO POULTRY A/S"}, {"OperationalStatus": "Active", "LFY": "2022-12-31", "LegalForm": "Limited_company", "Website": "www.miron.dk", "label": "Company", "CompanyInfoUpdatedDate": "2023-06-08", "DescriptionEN": "The purpose of the company is to own shares and shares as well as related business and investment.", "Signatory": "Selskabet tegnes af direkt\u00f8ren.", "ParentCompanyName": "House of Foods Holding ApS", "Name": "EURO POULTRY HOLDING ApS", "KeyPersonsUpdatedDate": "2023-10-14", "FiscalYearLength": 12.0, "RegistrationDate": "2005-09-21", "DataUpdatedDate": "2023-11-02", "OwnersUpdatedDate": "2023-05-19", "ListingType": "Unlisted", "OrgNo": "29166692", "FinancialDataCurrencyCode": "USD", "HasForeignUltimateParent": false, "Valu8Id": 7993267}, {"OperationalStatus": "Active", "LFY": "0001-01-01", "LegalForm": "Limited_company", "label": "Company", "CompanyInfoUpdatedDate": "2023-10-02", "DescriptionEN": "The purpose of the company is to own shares and shares as well as related business and investment.", "Signatory": "Selskabet tegnes af direkt\u00f8ren i forening med formanden for bestyrelsen samt n\u00e6stformanden for bestyrelsen.", "Name": "House of Foods Holding ApS", "KeyPersonsUpdatedDate": "2023-10-14", "RegistrationDate": "2023-04-19", "DataUpdatedDate": "2023-10-28", "OwnersUpdatedDate": "2023-05-17", "ListingType": "Unlisted", "OrgNo": "43995553", "FinancialDataCurrencyCode": "USD", "HasForeignUltimateParent": false, "Valu8Id": 250744692, "PreviousNames": "House of Foods ApS"}, {"OperationalStatus": "Active", "LFY": "2022-06-30", "Phone": "27855873", "LegalForm": "Limited_company", "label": "Company", "CompanyInfoUpdatedDate": "2023-09-27", "DescriptionEN": "The purpose of the company is to own shares in companies that are intended to conduct trading, investment and financing activities.", "Signatory": "Selskabet tegnes af en direkt\u00f8r eller af to bestyrelsesmedlemmer i\r\nforening eller af bestyrelsesformanden alene eller af den samlede bestyrelse.", "ParentCompanyName": "ES HOLDING AALBORG ApS", "Name": "Carsten M\u00f8ller Food Holding A/S", "KeyPersonsUpdatedDate": "2023-10-14", "FiscalYearLength": 12.0, "RegistrationDate": "2016-06-28", "DataUpdatedDate": "2023-10-28", "OwnersUpdatedDate": "2023-06-15", "ListingType": "Unlisted", "OrgNo": "37834017", "FinancialDataCurrencyCode": "USD", "HasForeignUltimateParent": false, "Valu8Id": 16129576}, {"OperationalStatus": "Active", "LFY": "2022-06-30", "Phone": "27855873", "LegalForm": "Limited_company", "label": "Company", "CompanyInfoUpdatedDate": "2023-09-27", "DescriptionEN": "The purpose of the Company is to hold shares in subsidiaries and associated companies, to conduct investment and financing activities and other related activities at the discretion of management.", "Signatory": "Selskabet tegnes af en direkt\u00f8r.", "Name": "ES HOLDING AALBORG ApS", "KeyPersonsUpdatedDate": "2023-10-14", "FiscalYearLength": 12.0, "RegistrationDate": "2003-03-14", "DataUpdatedDate": "2023-11-02", "OwnersUpdatedDate": "2022-09-05", "ListingType": "Unlisted", "OrgNo": "27074189", "FinancialDataCurrencyCode": "USD", "HasForeignUltimateParent": false, "Valu8Id": 7824427}, {"OperationalStatus": "Active", "LFY": "2022-06-30", "Phone": "27855873", "LegalForm": "Limited_company", "label": "Company", "CompanyInfoUpdatedDate": "2023-09-27", "DescriptionEN": "The purpose of the company is to own shares in other companies and thus, at the discretion of the Executive Board, related activities.", "Signatory": "Selskabet tegnes af en direkt\u00f8r.", "Name": "ALES Holding ApS", "KeyPersonsUpdatedDate": "2023-10-14", "FiscalYearLength": 12.0, "RegistrationDate": "2019-12-20", "DataUpdatedDate": "2023-10-28", "OwnersUpdatedDate": "2022-09-05", "ListingType": "Unlisted", "OrgNo": "41196378", "FinancialDataCurrencyCode": "USD", "HasForeignUltimateParent": false, "Valu8Id": 124617525}, {"Name": "Ejner S\u00f8rensen", "label": "Person", "Valu8Id": 201779305}, {"OperationalStatus": "Active", "LFY": "2022-06-30", "Phone": "53658481", "LegalForm": "Limited_company", "label": "Company", "CompanyInfoUpdatedDate": "2021-12-03", "DescriptionEN": "The purpose of the company is to own shares in other companies and thus, at the discretion of the Executive Board, related activities.", "Signatory": "Selskabet tegnes af en direkt\u00f8r.", "Name": "Janne Beyer Trudslev Holding ApS", "KeyPersonsUpdatedDate": "2023-10-14", "FiscalYearLength": 12.0, "RegistrationDate": "2019-12-20", "DataUpdatedDate": "2023-10-28", "OwnersUpdatedDate": "2022-09-05", "ListingType": "Unlisted", "OrgNo": "41196351", "FinancialDataCurrencyCode": "USD", "HasForeignUltimateParent": false, "Valu8Id": 124617513}, {"Name": "Janne Beyer Trudslev", "label": "Person", "Valu8Id": 201880022}, {"OperationalStatus": "Active", "LFY": "2022-06-30", "LegalForm": "Limited_company", "label": "Company", "CompanyInfoUpdatedDate": "2022-11-10", "DescriptionEN": "The purpose of the company is to own shares in other companies and thus, at the discretion of the Executive Board, related activities.", "Signatory": "Selskabet tegnes af en direkt\u00f8r.", "Name": "Camilla Beyer S\u00f8rensen Holding ApS", "KeyPersonsUpdatedDate": "2023-10-14", "FiscalYearLength": 12.0, "RegistrationDate": "2019-12-20", "DataUpdatedDate": "2023-10-28", "OwnersUpdatedDate": "2022-09-05", "ListingType": "Unlisted", "OrgNo": "41196335", "FinancialDataCurrencyCode": "USD", "HasForeignUltimateParent": false, "Valu8Id": 124617497}, {"Name": "Camilla Beyer S\u00f8rensen", "label": "Person", "Valu8Id": 202010624}, {"OperationalStatus": "Active", "LFY": "2022-06-30", "LegalForm": "Limited_company", "label": "Company", "CompanyInfoUpdatedDate": "2021-12-03", "DescriptionEN": "The purpose of the company is to own shares in other companies and thus, at the discretion of the Executive Board, related activities.", "Signatory": "Selskabet tegnes af en direkt\u00f8r.", "Name": "Rikke Beyer S\u00f8rensen Holding ApS", "KeyPersonsUpdatedDate": "2023-10-14", "FiscalYearLength": 12.0, "RegistrationDate": "2019-12-20", "DataUpdatedDate": "2023-10-28", "OwnersUpdatedDate": "2022-09-05", "ListingType": "Unlisted", "OrgNo": "41196343", "FinancialDataCurrencyCode": "USD", "HasForeignUltimateParent": false, "Valu8Id": 124617692}, {"Name": "Rikke Klitg\u00e5rd Beyer S\u00f8rensen", "label": "Person", "Valu8Id": 201779308}, {"OperationalStatus": "Active", "LFY": "0001-01-01", "LegalForm": "Limited_company", "label": "Company", "CompanyInfoUpdatedDate": "9999-12-31", "DescriptionEN": "The purpose of the company is to own shares in other companies and matters that are naturally related thereto.", "Signatory": "Selskabet tegnes af 1 direkt\u00f8r.", "Name": "Morten Vangsted Holding ApS", "KeyPersonsUpdatedDate": "2023-10-14", "RegistrationDate": "2023-06-02", "DataUpdatedDate": "2023-10-28", "OwnersUpdatedDate": "2023-06-15", "ListingType": "Unlisted", "OrgNo": "44099950", "FinancialDataCurrencyCode": "USD", "HasForeignUltimateParent": false, "Valu8Id": 252497135}, {"Name": "Morten M\u00f8ller Vangsted", "label": "Person", "Valu8Id": 201744157}]}